[
  {"symbol":"BTCUSDT","qty":"0.025","price":"42350.50","commission":"0.00002500","commissionAsset":"BTC","isBuyer":true,"time":1738520000000,"orderId":12345001,"id":1001},
  {"symbol":"BTCUSDT","qty":"0.025","price":"41200.80","commission":"1.030020","commissionAsset":"USDT","isBuyer":false,"time":1738534400000,"orderId":12345002,"id":1002},
  {"symbol":"ETHUSDT","qty":"0.5","price":"2450.30","commission":"0.00050000","commissionAsset":"ETH","isBuyer":true,"time":1738548800000,"orderId":12345003,"id":1003},
  {"symbol":"ETHUSDT","qty":"0.5","price":"2320.75","commission":"1.160375","commissionAsset":"USDT","isBuyer":false,"time":1738563200000,"orderId":12345004,"id":1004},
  {"symbol":"DOGEUSDT","qty":"3000","price":"0.178","commission":"3.00000000","commissionAsset":"DOGE","isBuyer":true,"time":1738570000000,"orderId":12345005,"id":1005},
  {"symbol":"DOGEUSDT","qty":"3000","price":"0.152","commission":"0.456000","commissionAsset":"USDT","isBuyer":false,"time":1738580000000,"orderId":12345006,"id":1006},
  {"symbol":"SOLUSDT","qty":"20","price":"105.50","commission":"0.02000000","commissionAsset":"SOL","isBuyer":true,"time":1738577600000,"orderId":12345007,"id":1007},
  {"symbol":"SOLUSDT","qty":"20","price":"92.30","commission":"1.846000","commissionAsset":"USDT","isBuyer":false,"time":1738606400000,"orderId":12345008,"id":1008},
  {"symbol":"PEPEUSDT","qty":"20000000","price":"0.00001150","commission":"20000.00000000","commissionAsset":"PEPE","isBuyer":true,"time":1738610000000,"orderId":12345009,"id":1009},
  {"symbol":"PEPEUSDT","qty":"20000000","price":"0.00000890","commission":"0.178000","commissionAsset":"USDT","isBuyer":false,"time":1738615000000,"orderId":12345010,"id":1010},
  {"symbol":"WIFUSDT","qty":"400","price":"1.95","commission":"0.40000000","commissionAsset":"WIF","isBuyer":true,"time":1738618000000,"orderId":12345011,"id":1011},
  {"symbol":"WIFUSDT","qty":"400","price":"1.58","commission":"0.632000","commissionAsset":"USDT","isBuyer":false,"time":1738625000000,"orderId":12345012,"id":1012},
  {"symbol":"BTCUSDT","qty":"0.030","price":"43500.00","commission":"0.00003000","commissionAsset":"BTC","isBuyer":true,"time":1738620800000,"orderId":12345013,"id":1013},
  {"symbol":"BTCUSDT","qty":"0.030","price":"42100.50","commission":"1.263015","commissionAsset":"USDT","isBuyer":false,"time":1738634400000,"orderId":12345014,"id":1014},
  {"symbol":"SHIBUSDT","qty":"30000000","price":"0.00001180","commission":"30000.00000000","commissionAsset":"SHIB","isBuyer":true,"time":1738638000000,"orderId":12345015,"id":1015},
  {"symbol":"SHIBUSDT","qty":"30000000","price":"0.00000950","commission":"0.285000","commissionAsset":"USDT","isBuyer":false,"time":1738645000000,"orderId":12345016,"id":1016},
  {"symbol":"ADAUSDT","qty":"800","price":"0.62","commission":"0.80000000","commissionAsset":"ADA","isBuyer":true,"time":1738648800000,"orderId":12345017,"id":1017},
  {"symbol":"ADAUSDT","qty":"800","price":"0.54","commission":"0.432000","commissionAsset":"USDT","isBuyer":false,"time":1738677600000,"orderId":12345018,"id":1018},
  {"symbol":"BONKUSDT","qty":"8000000","price":"0.000022","commission":"8000.00000000","commissionAsset":"BONK","isBuyer":true,"time":1738680000000,"orderId":12345019,"id":1019},
  {"symbol":"BONKUSDT","qty":"8000000","price":"0.000018","commission":"0.144000","commissionAsset":"USDT","isBuyer":false,"time":1738685000000,"orderId":12345020,"id":1020},
  {"symbol":"ETHUSDT","qty":"0.8","price":"2580.00","commission":"0.00080000","commissionAsset":"ETH","isBuyer":true,"time":1738692000000,"orderId":12345021,"id":1021},
  {"symbol":"ETHUSDT","qty":"0.8","price":"2450.25","commission":"1.960200","commissionAsset":"USDT","isBuyer":false,"time":1738706400000,"orderId":12345022,"id":1022},
  {"symbol":"AVAXUSDT","qty":"50","price":"32.50","commission":"0.05000000","commissionAsset":"AVAX","isBuyer":true,"time":1738710000000,"orderId":12345023,"id":1023},
  {"symbol":"AVAXUSDT","qty":"50","price":"28.80","commission":"1.440000","commissionAsset":"USDT","isBuyer":false,"time":1738718000000,"orderId":12345024,"id":1024},
  {"symbol":"BNBUSDT","qty":"4","price":"325.80","commission":"0.00400000","commissionAsset":"BNB","isBuyer":true,"time":1738720800000,"orderId":12345025,"id":1025},
  {"symbol":"BNBUSDT","qty":"4","price":"302.50","commission":"1.210000","commissionAsset":"USDT","isBuyer":false,"time":1738749600000,"orderId":12345026,"id":1026},
  {"symbol":"FETUSDT","qty":"1000","price":"1.58","commission":"1.00000000","commissionAsset":"FET","isBuyer":true,"time":1738752000000,"orderId":12345027,"id":1027},
  {"symbol":"FETUSDT","qty":"1000","price":"1.42","commission":"1.420000","commissionAsset":"USDT","isBuyer":false,"time":1738758000000,"orderId":12345028,"id":1028},
  {"symbol":"DOTUSDT","qty":"80","price":"7.85","commission":"0.08000000","commissionAsset":"DOT","isBuyer":true,"time":1738764000000,"orderId":12345029,"id":1029},
  {"symbol":"DOTUSDT","qty":"80","price":"7.15","commission":"0.572000","commissionAsset":"USDT","isBuyer":false,"time":1738778400000,"orderId":12345030,"id":1030},
  {"symbol":"RENDERUSDT","qty":"250","price":"6.40","commission":"0.25000000","commissionAsset":"RENDER","isBuyer":true,"time":1738780000000,"orderId":12345031,"id":1031},
  {"symbol":"RENDERUSDT","qty":"250","price":"5.85","commission":"1.462500","commissionAsset":"USDT","isBuyer":false,"time":1738788000000,"orderId":12345032,"id":1032},
  {"symbol":"BTCUSDT","qty":"0.020","price":"44800.00","commission":"0.00002000","commissionAsset":"BTC","isBuyer":true,"time":1738792800000,"orderId":12345033,"id":1033},
  {"symbol":"BTCUSDT","qty":"0.020","price":"43200.75","commission":"0.864015","commissionAsset":"USDT","isBuyer":false,"time":1738821600000,"orderId":12345034,"id":1034},
  {"symbol":"ARBUSDT","qty":"900","price":"1.28","commission":"0.90000000","commissionAsset":"ARB","isBuyer":true,"time":1738825000000,"orderId":12345035,"id":1035},
  {"symbol":"ARBUSDT","qty":"900","price":"1.15","commission":"1.035000","commissionAsset":"USDT","isBuyer":false,"time":1738830000000,"orderId":12345036,"id":1036},
  {"symbol":"LINKUSDT","qty":"40","price":"16.80","commission":"0.04000000","commissionAsset":"LINK","isBuyer":true,"time":1738836000000,"orderId":12345037,"id":1037},
  {"symbol":"LINKUSDT","qty":"40","price":"15.20","commission":"0.608000","commissionAsset":"USDT","isBuyer":false,"time":1738850400000,"orderId":12345038,"id":1038},
  {"symbol":"JUPUSDT","qty":"700","price":"0.98","commission":"0.70000000","commissionAsset":"JUP","isBuyer":true,"time":1738854000000,"orderId":12345039,"id":1039},
  {"symbol":"JUPUSDT","qty":"700","price":"0.82","commission":"0.574000","commissionAsset":"USDT","isBuyer":false,"time":1738860000000,"orderId":12345040,"id":1040},
  {"symbol":"DOGEUSDT","qty":"2500","price":"0.168","commission":"2.50000000","commissionAsset":"DOGE","isBuyer":true,"time":1738863000000,"orderId":12345041,"id":1041},
  {"symbol":"DOGEUSDT","qty":"2500","price":"0.148","commission":"0.370000","commissionAsset":"USDT","isBuyer":false,"time":1738866000000,"orderId":12345042,"id":1042},
  {"symbol":"PEPEUSDT","qty":"18000000","price":"0.00001080","commission":"18000.00000000","commissionAsset":"PEPE","isBuyer":true,"time":1738869000000,"orderId":12345043,"id":1043},
  {"symbol":"SOLUSDT","qty":"15","price":"142.50","commission":"0.01500000","commissionAsset":"SOL","isBuyer":true,"time":1738880000000,"orderId":12345045,"id":1045},
  {"symbol":"SOLUSDT","qty":"15","price":"148.20","commission":"2.223000","commissionAsset":"USDT","isBuyer":false,"time":1738890000000,"orderId":12345046,"id":1046},
  {"symbol":"AVAXUSDT","qty":"50","price":"38.40","commission":"0.05000000","commissionAsset":"AVAX","isBuyer":true,"time":1738895000000,"orderId":12345047,"id":1047},
  {"symbol":"AVAXUSDT","qty":"50","price":"35.80","commission":"1.790000","commissionAsset":"USDT","isBuyer":false,"time":1738905000000,"orderId":12345048,"id":1048},
  {"symbol":"MATICUSDT","qty":"2000","price":"0.92","commission":"2.00000000","commissionAsset":"MATIC","isBuyer":true,"time":1738910000000,"orderId":12345049,"id":1049},
  {"symbol":"MATICUSDT","qty":"2000","price":"0.88","commission":"1.760000","commissionAsset":"USDT","isBuyer":false,"time":1738920000000,"orderId":12345050,"id":1050},
  {"symbol":"DOTUSDT","qty":"200","price":"7.25","commission":"0.20000000","commissionAsset":"DOT","isBuyer":true,"time":1738925000000,"orderId":12345051,"id":1051},
  {"symbol":"DOTUSDT","qty":"200","price":"7.68","commission":"1.536000","commissionAsset":"USDT","isBuyer":false,"time":1738935000000,"orderId":12345052,"id":1052},
  {"symbol":"ATOMUSDT","qty":"120","price":"10.50","commission":"0.12000000","commissionAsset":"ATOM","isBuyer":true,"time":1738940000000,"orderId":12345053,"id":1053},
  {"symbol":"ATOMUSDT","qty":"120","price":"11.20","commission":"1.344000","commissionAsset":"USDT","isBuyer":false,"time":1738950000000,"orderId":12345054,"id":1054},
  {"symbol":"PEPEUSDT","qty":"18000000","price":"0.00000920","commission":"0.165600","commissionAsset":"USDT","isBuyer":false,"time":1738872000000,"orderId":12345044,"id":1044}
]